g42cloudsdksms/__init__.py
g42cloudsdksms/v3/__init__.py
g42cloudsdksms/v3/sms_async_client.py
g42cloudsdksms/v3/sms_client.py
g42cloudsdksms/v3/model/__init__.py
g42cloudsdksms/v3/model/btrfs_file_system.py
g42cloudsdksms/v3/model/btrfs_subvolumn.py
g42cloudsdksms/v3/model/check_net_acl_request.py
g42cloudsdksms/v3/model/check_net_acl_response.py
g42cloudsdksms/v3/model/clone_server.py
g42cloudsdksms/v3/model/clone_server_brief.py
g42cloudsdksms/v3/model/collect_log_request.py
g42cloudsdksms/v3/model/collect_log_response.py
g42cloudsdksms/v3/model/comand_param.py
g42cloudsdksms/v3/model/command_body.py
g42cloudsdksms/v3/model/config_body.py
g42cloudsdksms/v3/model/configuration_request_body.py
g42cloudsdksms/v3/model/create_migproject_request.py
g42cloudsdksms/v3/model/create_migproject_response.py
g42cloudsdksms/v3/model/create_task_request.py
g42cloudsdksms/v3/model/create_task_response.py
g42cloudsdksms/v3/model/create_template_req.py
g42cloudsdksms/v3/model/create_template_request.py
g42cloudsdksms/v3/model/create_template_response.py
g42cloudsdksms/v3/model/delete_ids.py
g42cloudsdksms/v3/model/delete_migproject_request.py
g42cloudsdksms/v3/model/delete_migproject_response.py
g42cloudsdksms/v3/model/delete_server_request.py
g42cloudsdksms/v3/model/delete_server_response.py
g42cloudsdksms/v3/model/delete_servers_request.py
g42cloudsdksms/v3/model/delete_servers_response.py
g42cloudsdksms/v3/model/delete_task_request.py
g42cloudsdksms/v3/model/delete_task_response.py
g42cloudsdksms/v3/model/delete_tasks_req.py
g42cloudsdksms/v3/model/delete_tasks_request.py
g42cloudsdksms/v3/model/delete_tasks_response.py
g42cloudsdksms/v3/model/delete_template_request.py
g42cloudsdksms/v3/model/delete_template_response.py
g42cloudsdksms/v3/model/delete_templates_request.py
g42cloudsdksms/v3/model/delete_templates_response.py
g42cloudsdksms/v3/model/deletetemplates_req.py
g42cloudsdksms/v3/model/disk.py
g42cloudsdksms/v3/model/disk_intarget_server.py
g42cloudsdksms-0.0.10b0.dist-info/LICENSE
g42cloudsdksms-0.0.10b0.dist-info/METADATA
g42cloudsdksms-0.0.10b0.dist-info/WHEEL
g42cloudsdksms-0.0.10b0.dist-info/top_level.txt
g42cloudsdksms-0.0.10b0.dist-info/RECORD
